mxdesign/__init__.py
mxdesign/entities/__init__.py
mxdesign/entities/base.py
mxdesign/entities/environment.py
mxdesign/entities/experiment.py
mxdesign/entities/namespace.py
mxdesign/entities/trial.py
mxdesign/entities/value.py
mxdesign/entities/variable.py
mxdesign/utils/__init__.py
mxdesign/utils/dict.py
mxdesign/utils/pandas.py
mxdesign-0.0.5.dist-info/LICENSE
mxdesign-0.0.5.dist-info/METADATA
mxdesign-0.0.5.dist-info/WHEEL
mxdesign-0.0.5.dist-info/top_level.txt
mxdesign-0.0.5.dist-info/RECORD
