Metadata-Version: 2.1
Name: mxdesign
Version: 0.0.5
Summary: A framework for eXperiment design specification
Classifier: Programming Language :: Python :: 3
Classifier: License :: OSI Approved :: MIT License
Classifier: Operating System :: OS Independent
Requires-Python: >=3.7
License-File: LICENSE
